lbcharmdb/__init__.py
lbcharmdb/calculate_correlations_weighted_tuples.py
lbcharmdb/database.py
lbcharmdb/db_classes.py
lbcharmdb/publisher.py
lbcharmdb/units.py
lbcharmdb/utilities.py
lbcharmdb-0.11.dist-info/LICENSE
lbcharmdb-0.11.dist-info/METADATA
lbcharmdb-0.11.dist-info/WHEEL
lbcharmdb-0.11.dist-info/entry_points.txt
lbcharmdb-0.11.dist-info/top_level.txt
lbcharmdb-0.11.dist-info/RECORD
