Metadata-Version: 2.1
Name: lbcharmdb
Version: 0.11
Summary: Maintenance tools for the database of correlations between charm analyses
Home-page: https://gitlab.cern.ch/lhcb-charm/correlations-database-editor
Author: Laurent Dufour
Author-email: Laurent Dufour <laurent.dufour@cern.ch>
Project-URL: Homepage, https://gitlab.cern.ch/lhcb-charm/correlations-database-editor
Project-URL: Bug Reports, https://gitlab.cern.ch/lhcb-charm/correlations-database-editor/issues
Project-URL: Source, https://gitlab.cern.ch/lhcb-charm/correlations-database-editor
Keywords: LHCb,charm
Classifier: Development Status :: 4 - Beta
Classifier: License :: OSI Approved :: GNU General Public License v3 or later (GPLv3+)
Classifier: Operating System :: OS Independent
Classifier: Programming Language :: Python :: 3
Requires-Python: >=3.8
License-File: LICENSE
Requires-Dist: tqdm
Requires-Dist: numpy
Requires-Dist: coloredlogs
